README.rst
setup.py
iOrder.egg-info/PKG-INFO
iOrder.egg-info/SOURCES.txt
iOrder.egg-info/dependency_links.txt
iOrder.egg-info/entry_points.txt
iOrder.egg-info/requires.txt
iOrder.egg-info/top_level.txt
order/XYZ.py
order/__init__.py
order/avc.py
order/interface.py
order/ionic.py
order/lsi.py
order/msd.py
order/order.py
order/oto.py
order/plot.py
order/soq.py
order/tto.py
order/util.py
tests/__init__.py
tests/test_order.py