Metadata-Version: 1.1
Name: iOrder
Version: 0.0.3
Summary: A tool to characterize the local structure of liquid water by geometric order parameters
Home-page: https://github.com/ipudu/order
Author: Pu Du
Author-email: pudugg@gmail.com
License: MIT
Keywords: order parameter,water structure
Platform: UNKNOWN
Classifier: Development Status :: 2 - Pre-Alpha
Classifier: Environment :: Console
Classifier: License :: OSI Approved :: MIT License
Classifier: Programming Language :: Python :: 2.7
Classifier: Programming Language :: Python :: 3.4
Classifier: Programming Language :: Python :: 3.5
Classifier: Programming Language :: Python :: 3.6
Classifier: Topic :: Scientific/Engineering :: Chemistry
Classifier: Topic :: Scientific/Engineering :: Physics
